Panozzo_libreria/__init__.py
panozzo_libreria-0.1.0.dist-info/METADATA
panozzo_libreria-0.1.0.dist-info/WHEEL
panozzo_libreria-0.1.0.dist-info/licenses/LICENSE.txt
panozzo_libreria-0.1.0.dist-info/RECORD
