Metadata-Version: 2.4
Name: Panozzo_libreria
Version: 0.1.0
Summary: Una librería de calculo simple
Author-email: Sebastian Panozzo <panozzosebastian02@email.com>
License: MIT
License-File: LICENSE.txt
